[ {
  "id" : "659cb764-82e6-0993-992f-a487f7defdac",
  "name" : "our_client",
  "display_width" : null,
  "label" : "Our Client",
  "required" : false,
  "locked" : false,
  "occurrence" : {
    "min" : null,
    "max" : null,
    "sorting_label_field" : "0adc9ef1-e55d-dad4-934e-23c145b85830",
    "default" : 1
  },
  "children" : [ {
    "id" : "0adc9ef1-e55d-dad4-934e-23c145b85830",
    "name" : "logo",
    "display_width" : null,
    "label" : "Logo",
    "required" : false,
    "locked" : false,
    "responsive" : true,
    "resizable" : true,
    "show_loading" : false,
    "type" : "image",
    "default" : {
      "size_type" : "auto",
      "src" : "https://21128909.fs1.hubspotusercontent-na1.net/hubfs/21128909/KpcTeam_January2023/Image/abbott.jpg",
      "alt" : "abbott",
      "loading" : "lazy",
      "width" : 304,
      "height" : 123,
      "max_width" : 304,
      "max_height" : 123
    }
  } ],
  "tab" : "CONTENT",
  "expanded" : false,
  "type" : "group",
  "default" : [ {
    "logo" : {
      "size_type" : "auto",
      "src" : "https://21128909.fs1.hubspotusercontent-na1.net/hubfs/21128909/KpcTeam_January2023/Image/abbott.jpg",
      "alt" : "abbott",
      "loading" : "lazy",
      "width" : 304,
      "height" : 123,
      "max_width" : 304,
      "max_height" : 123
    }
  } ]
} ]